rabbitqueues/__init__.py
rabbitqueues/abstract_manager.py
rabbitqueues/apps.py
rabbitqueues/management/__init__.py
rabbitqueues/management/commands/__init__.py
rabbitqueues/management/commands/db_queue_consumer.py
rabbitqueues_beeflow-0.0.7.dist-info/LICENCE
rabbitqueues_beeflow-0.0.7.dist-info/METADATA
rabbitqueues_beeflow-0.0.7.dist-info/WHEEL
rabbitqueues_beeflow-0.0.7.dist-info/top_level.txt
rabbitqueues_beeflow-0.0.7.dist-info/RECORD
