Metadata-Version: 2.1
Name: rabbitqueues-beeflow
Version: 0.0.7
Summary: Application to manage RabbitMQ queues
Home-page: https://github.com/beeflow/rabbit_queues.git
Author: Rafal Przetakowski
Author-email: office@beeflow.co.uk
License: UNKNOWN
Platform: UNKNOWN
Classifier: Programming Language :: Python :: 3
Classifier: License :: OSI Approved :: MIT License
Classifier: Operating System :: OS Independent
Requires-Python: >=3.8
